setup.py
example/__init__.py
example/example_IForest.py
lisite_lib/__init__.py
lisite_lib.egg-info/PKG-INFO
lisite_lib.egg-info/SOURCES.txt
lisite_lib.egg-info/dependency_links.txt
lisite_lib.egg-info/requires.txt
lisite_lib.egg-info/top_level.txt
lisite_lib/algorithms/IForest.py
lisite_lib/algorithms/__init__.py
lisite_lib/utils/__init__.py
lisite_lib/utils/consts.py