Metadata-Version: 2.1
Name: lisite_lib
Version: 1.0.0
Author: Lisite
Classifier: Programming Language :: Python :: 3
Classifier: License :: OSI Approved :: MIT License
Classifier: Operating System :: OS Independent
Requires-Dist: numpy
Requires-Dist: pandas
